fslib/__init__.py
fslib/base.py
fslib/builders.py
fslib/exceptions.py
fslib/helpers.py
fslib/stacking.py
fslib-0.3.4.dist-info/METADATA
fslib-0.3.4.dist-info/WHEEL
fslib-0.3.4.dist-info/top_level.txt
fslib-0.3.4.dist-info/RECORD
