Metadata-Version: 2.1
Name: fslib
Version: 0.3.4
Summary: Wrapper around low-level FS-related calls, with support for advanced FS stacking
Home-page: https://github.com/rbarrois/fslib/
Author: Raphaël Barrois
Author-email: raphael.barrois+fslib@polytechnique.org
License: BSD
Download-URL: https://pypi.python.org/pypi/fslib/
Keywords: FS,FileSystem,UnionFS,os
Platform: OS Independent
Classifier: Development Status :: 4 - Beta
Classifier: Intended Audience :: Developers
Classifier: Intended Audience :: System Administrators
Classifier: License :: OSI Approved :: BSD License
Classifier: Operating System :: OS Independent
Classifier: Programming Language :: Python :: 3
Classifier: Topic :: Software Development :: Libraries :: Python Modules
Classifier: Topic :: System :: Filesystems
